{
  "880218394199220334": {
    "boostLevel": 0,
    "maxParticipants": -1
  },
  "755827207812677713": {
    "boostLevel": 1,
    "maxParticipants": 25
  },
  "773336526917861400": {
    "boostLevel": 0,
    "maxParticipants": -1
  },
  "814288819477020702": {
    "boostLevel": 0,
    "maxParticipants": -1
  },
  "832012774040141894": {
    "boostLevel": 1,
    "maxParticipants": -1
  },
  "879864070101172255": {
    "boostLevel": 0,
    "maxParticipants": 12
  },
  "879863881349087252": {
    "boostLevel": 0,
    "maxParticipants": 12
  },
  "878067389634314250": {
    "boostLevel": 0,
    "maxParticipants": 16
  },
  "902271654783242291": {
    "boostLevel": 0,
    "maxParticipants": 16
  },
  "879863686565621790": {
    "boostLevel": 1,
    "maxParticipants": 8
  },
  "879863976006127627": {
    "boostLevel": 0,
    "maxParticipants": 8
  },
  "852509694341283871": {
    "boostLevel": 1,
    "maxParticipants": 100
  },
  "832013003968348200": {
    "boostLevel": 1,
    "maxParticipants": -1
  },
  "832025144389533716": {
    "boostLevel": 1,
    "maxParticipants": 8
  },
  "945737671223947305": {
    "boostLevel": 1,
    "maxParticipants": -1
  },
  "903769130790969345": {
    "boostLevel": 1,
    "maxParticipants": 16
  },
  "947957217959759964": {
    "boostLevel": 1,
    "maxParticipants": 8
  },
  "976052223358406656": {
    "boostLevel": 0,
    "maxParticipants": 10
  },
  "950505761862189096": {
    "boostLevel": 0,
    "maxParticipants": 8
  },
  "1006584476094177371": {
    "boostLevel": 0,
    "maxParticipants": 16
  }
}